pattern_analysis/__init__.py
pattern_analysis/pattern_analysis.py
pattern_analysis-0.1.2.dist-info/AUTHORS.rst
pattern_analysis-0.1.2.dist-info/LICENSE
pattern_analysis-0.1.2.dist-info/METADATA
pattern_analysis-0.1.2.dist-info/WHEEL
pattern_analysis-0.1.2.dist-info/top_level.txt
pattern_analysis-0.1.2.dist-info/RECORD
