Metadata-Version: 2.1
Name: pattern-analysis
Version: 0.1.2
Summary: A package for analyzing patterns in biological data.
Home-page: https://github.com/ScienceComputing/pattern_analysis
Author: Anni Liu
Author-email: anni.liu009@gmail.com
License: MIT license
Keywords: pattern_analysis
Classifier: Development Status :: 2 - Pre-Alpha
Classifier: Intended Audience :: Developers
Classifier: License :: OSI Approved :: MIT License
Classifier: Natural Language :: English
Classifier: Programming Language :: Python :: 3
Classifier: Programming Language :: Python :: 3.6
Classifier: Programming Language :: Python :: 3.7
Classifier: Programming Language :: Python :: 3.8
Requires-Python: >=3.6
License-File: LICENSE
License-File: AUTHORS.rst
